jupyterlab_js/__init__.py
jupyterlab_js/py.typed
jupyterlab_js-4.5.3.data/data/share/jupyter/lab/schemas/@jupyterlab/application-extension/commands.json
jupyterlab_js-4.5.3.data/data/share/jupyter/lab/schemas/@jupyterlab/application-extension/context-menu.json
jupyterlab_js-4.5.3.data/data/share/jupyter/lab/schemas/@jupyterlab/application-extension/package.json.orig
jupyterlab_js-4.5.3.data/data/share/jupyter/lab/schemas/@jupyterlab/application-extension/property-inspector.json
jupyterlab_js-4.5.3.data/data/share/jupyter/lab/schemas/@jupyterlab/application-extension/shell.json
jupyterlab_js-4.5.3.data/data/share/jupyter/lab/schemas/@jupyterlab/application-extension/top-bar.json
jupyterlab_js-4.5.3.data/data/share/jupyter/lab/schemas/@jupyterlab/apputils-extension/kernels-settings.json
jupyterlab_js-4.5.3.data/data/share/jupyter/lab/schemas/@jupyterlab/apputils-extension/notification.json
jupyterlab_js-4.5.3.data/data/share/jupyter/lab/schemas/@jupyterlab/apputils-extension/package.json.orig
jupyterlab_js-4.5.3.data/data/share/jupyter/lab/schemas/@jupyterlab/apputils-extension/palette.json
jupyterlab_js-4.5.3.data/data/share/jupyter/lab/schemas/@jupyterlab/apputils-extension/print.json
jupyterlab_js-4.5.3.data/data/share/jupyter/lab/schemas/@jupyterlab/apputils-extension/sanitizer.json
jupyterlab_js-4.5.3.data/data/share/jupyter/lab/schemas/@jupyterlab/apputils-extension/sessionDialogs.json
jupyterlab_js-4.5.3.data/data/share/jupyter/lab/schemas/@jupyterlab/apputils-extension/themes.json
jupyterlab_js-4.5.3.data/data/share/jupyter/lab/schemas/@jupyterlab/apputils-extension/utilityCommands.json
jupyterlab_js-4.5.3.data/data/share/jupyter/lab/schemas/@jupyterlab/cell-toolbar-extension/package.json.orig
jupyterlab_js-4.5.3.data/data/share/jupyter/lab/schemas/@jupyterlab/cell-toolbar-extension/plugin.json
jupyterlab_js-4.5.3.data/data/share/jupyter/lab/schemas/@jupyterlab/celltags-extension/package.json.orig
jupyterlab_js-4.5.3.dist-info/METADATA
jupyterlab_js-4.5.3.dist-info/WHEEL
jupyterlab_js-4.5.3.dist-info/licenses/LICENSE
jupyterlab_js-4.5.3.dist-info/RECORD
